{
    "Offices": {
        "1F": {
            "Old Building": [
                {
                    "id": "OB1",
                    "name": "Registrar",
                    "category": "Offices",
                    "floor": "1st Floor / 1F / Ground",
                    "imageFileName": "registrar",
                    "building": "Old Building",
                    "coordinates": {
                        "latitude": 6.117952,
                        "longitude": 125.145189
                    }
                },
                {
                    "id": "OB2",
                    "name": "VP for Administration & VP for Academic Affairs",
                    "category": "Offices",
                    "floor": "1st Floor / 1F / Ground",
                    "building": "Old Building",
                    "imageFileName": "vp-aca-admin",
                    "coordinates": {
                        "latitude": 6.117910,
                        "longitude": 125.145078
                    }
                },
                {
                    "id": "OB3",
                    "name": "HRDO",
                    "category": "Offices",
                    "floor": "1st Floor / 1F / Ground",
                    "building": "Old Building",
                    "imageFileName": "hrdo-cashier",
                    "coordinates": {
                        "latitude": 6.117891,
                        "longitude": 125.145017
                    }
                },
                {
                    "id": "OB4",
                    "name": "Cashier",
                    "category": "Offices",
                    "floor": "1st Floor / 1F / Ground",
                    "imageFileName": "hrdo-cashier",
                    "building": "Old Building",
                    "coordinates": {
                        "latitude": 6.117872,
                        "longitude": 125.144967
                    }
                },
                {
                    "id": "OB5",
                    "name": "Guidance and Counseling Center",
                    "category": "Offices",
                    "floor": "1st Floor / 1F / Ground",
                    "building": "Old Building",
                    "imageFileName": "guide-counsel",
                    "coordinates": {
                        "latitude": 6.117849,
                        "longitude": 125.144917
                    }
                },
                {
                    "id": "OB6",
                    "name": "GAD Office",
                    "category": "Offices",
                    "floor": "1st Floor / 1F / Ground",
                    "building": "Old Building",
                    "imageFileName": "gad",
                    "coordinates": {
                        "latitude": 6.117802,
                        "longitude": 125.144767
                    }
                },
                {
                    "id": "OB7",
                    "name": "Clinic & Office of the Scholarship Coordinator",
                    "category": "Offices",
                    "floor": "1st Floor / 1F / Ground",
                    "building": "Old Building",
                    "imageFileName": "clinic-scholar",
                    "coordinates": {
                        "latitude": 6.117771,
                        "longitude": 125.144680
                    }
                },
                {
                    "id": "OB8",
                    "name": "Simulation Room",
                    "category": "Offices",
                    "floor": "1st Floor / 1F / Ground",
                    "building": "Old Building",
                    "imageFileName": "simul-old",
                    "coordinates": {
                        "latitude": 6.117732,
                        "longitude": 125.144590
                    }
                },
                {
                    "id": "OB9",
                    "name": "BSNAME Department Head Office",
                    "category": "Offices",
                    "floor": "1st Floor / 1F / Ground",
                    "building": "Old Building",
                    "imageFileName": "bsname-dept-rm-102",
                    "coordinates": {
                        "latitude": 6.117682,
                        "longitude": 125.144468
                    }
                }
            ],
            "Gym Building": [
                {
                    "id": "GB2",
                    "name": "BSME Department Office",
                    "category": "Offices",
                    "floor": "1st Floor / 1F / Ground",
                    "building": "Gym Building",
                    "imageFileName": "bsme-dept-office",
                    "coordinates": {
                        "latitude": 6.117363,
                        "longitude": 125.144802
                    }
                },
                {
                    "id": "GB3",
                    "name": "BSME Department Head & BSIT Department Head",
                    "category": "Offices",
                    "floor": "1st Floor / 1F / Ground",
                    "building": "Gym Building",
                    "imageFileName": "bsme-bsit-dept-head",
                    "coordinates": {
                        "latitude": 6.117385,
                        "longitude": 125.144857
                    }
                },
                {
                    "id": "GB4",
                    "name": "BSCA Department Head",
                    "category": "Offices",
                    "floor": "1st Floor / 1F / Ground",
                    "building": "Gym Building",
                    "imageFileName": "bsca-dept-head",
                    "coordinates": {
                        "latitude": 6.117409,
                        "longitude": 125.144913
                    }
                },
                {
                    "id": "GB5",
                    "name": "Research and Developmentt Office",
                    "category": "Offices",
                    "floor": "1st Floor / 1F / Ground",
                    "building": "Gym Building",
                    "imageFileName": "res-dev",
                    "coordinates": {
                        "latitude": 6.117430,
                        "longitude": 125.144966
                    }
                },
                {
                    "id": "GB6",
                    "name": "Office of the Practicum Coordinator",
                    "category": "Offices",
                    "floor": "1st Floor / 1F / Ground",
                    "building": "Gym Building",
                    "imageFileName": "prac-coo",
                    "coordinates": {
                        "latitude": 6.117448,
                        "longitude": 125.145049
                    }
                },
                {
                    "id": "GB7",
                    "name": "Porthole",
                    "category": "Offices",
                    "floor": "1st Floor / 1F / Ground",
                    "building": "Gym Building",
                    "imageFileName": "porthole",
                    "coordinates": {
                        "latitude": 6.117463,
                        "longitude": 125.145100
                    }
                },
                {
                    "id": "GB8",
                    "name": "Quality Assurance Manager",
                    "category": "Offices",
                    "floor": "1st Floor / 1F / Ground",
                    "building": "Gym Building",
                    "imageFileName": "qam",
                    "coordinates": {
                        "latitude": 6.117491,
                        "longitude": 125.145163
                    }
                },
                {
                    "id": "GB9",
                    "name": "Office of the SHS Principal",
                    "category": "Offices",
                    "floor": "1st Floor / 1F / Ground",
                    "building": "Gym Building",
                    "imageFileName": "shs-ssg-plant",
                    "coordinates": {
                        "latitude": 6.117799,
                        "longitude": 125.145024
                    }
                },
                {
                    "id": "GB10",
                    "name": "Supreme Student Government / SHS Department",
                    "category": "Offices",
                    "floor": "1st Floor / 1F / Ground",
                    "building": "Gym Building",
                    "imageFileName": "shs-ssg-plant",
                    "coordinates": {
                        "latitude": 6.117788,
                        "longitude": 125.144994
                    }
                },
                {
                    "id": "GB11",
                    "name": "Physical Plant Office",
                    "category": "Offices",
                    "floor": "1st Floor / 1F / Ground",
                    "building": "Gym Building",
                    "imageFileName": "shs-ssg-plant",
                    "coordinates": {
                        "latitude": 6.117781,
                        "longitude": 125.144974
                    }
                },
                {
                    "id": "GB18",
                    "name": "Anchor Office",
                    "category": "Offices",
                    "floor": "1st Floor / 1F / Ground",
                    "building": "Gym Building",
                    "imageFileName": "pscas-anchor",
                    "coordinates": {
                        "latitude": 6.117777,
                        "longitude": 125.144963
                    }
                },
                {
                    "id": "GB12",
                    "name": "Philippine Security of Customs Administration Students (PSCAS)",
                    "category": "Offices",
                    "floor": "1st Floor / 1F / Ground",
                    "building": "Gym Building",
                    "imageFileName": "pscas-anchor",
                    "coordinates": {
                        "latitude": 6.117769,
                        "longitude": 125.144950
                    }
                },
                {
                    "id": "GB13",
                    "name": "Office of the Supreme Student Council",
                    "category": "Offices",
                    "floor": "1st Floor / 1F / Ground",
                    "building": "Gym Building",
                    "imageFileName": "naval-arch-ssc",
                    "coordinates": {
                        "latitude": 6.117736,
                        "longitude": 125.144874
                    }
                },
                {
                    "id": "GB14",
                    "name": "Society of Naval Architecture & Marine Engineering Students",
                    "category": "Offices",
                    "floor": "1st Floor / 1F / Ground",
                    "building": "Gym Building",
                    "imageFileName": "naval-arch-ssc",
                    "coordinates": {
                        "latitude": 6.117735,
                        "longitude": 125.144857
                    }
                },
                {
                    "id": "GB15",
                    "name": "Office of the Hospitality Department",
                    "category": "Offices",
                    "floor": "1st Floor / 1F / Ground",
                    "building": "Gym Building",
                    "imageFileName": "hospitality",
                    "coordinates": {
                        "latitude": 6.117720,
                        "longitude": 125.144820
                    }
                },
                {
                    "id": "GB16",
                    "name": "Office of Student Activities & Services (OSAS) / NSTP Office",
                    "category": "Offices",
                    "floor": "1st Floor / 1F / Ground",
                    "building": "Gym Building",
                    "imageFileName": "osas-nstp",
                    "coordinates": {
                        "latitude": 6.117703,
                        "longitude": 125.144774
                    }
                },
                {
                    "id": "GB17",
                    "name": "Sports Office",
                    "category": "Offices",
                    "floor": "1st Floor / 1F / Ground",
                    "building": "Gym Building",
                    "imageFileName": "sports",
                    "coordinates": {
                        "latitude": 6.117686,
                        "longitude": 125.144732
                    }
                }
            ],
            "Maritime Building": [
                {
                    "id": "MB1F-9",
                    "name": "Dean of Maritime Education Office",
                    "category": "Offices",
                    "floor": "1st Floor / 1F / Ground",
                    "building": "Maritime Building",
                    "imageFileName": "dean-maritime",
                    "coordinates": {
                        "latitude": 6.117157,
                        "longitude": 125.144878
                    }
                },
                {
                    "id": "MB1F-15",
                    "name": "Front Office Lab",
                    "category": "Offices",
                    "floor": "1st Floor / 1F / Ground",
                    "building": "Maritime Building",
                    "imageFileName": "front-office",
                    "coordinates": {
                        "latitude": 6.117132,
                        "longitude": 125.144518
                    }
                }
            ],
            "Mar-E": [
                {
                    "id": "MAR1F-1",
                    "name": "MPC Tech-Voc Office",
                    "category": "Offices",
                    "floor": "1st Floor / 1F / Ground",
                    "building": "Mar-E",
                    "imageFileName": "tec-voc",
                    "coordinates": {
                        "latitude": 6.117180,
                        "longitude": 125.143990
                    }
                }
            ],
            "Outside": [
                {
                    "id": "O-3",
                    "name": "Property Custodian",
                    "category": "Offices",
                    "floor": "1st Floor / 1F / Ground",
                    "building": "Outside",
                    "imageFileName": "property-electric",
                    "coordinates": {
                        "latitude": 6.116869,
                        "longitude": 125.144185
                    }
                },
                {
                    "id": "O-4",
                    "name": "Electrical Department",
                    "category": "Offices",
                    "floor": "1st Floor / 1F / Ground",
                    "building": "Outside",
                    "imageFileName": "property-electric",
                    "coordinates": {
                        "latitude": 6.116824,
                        "longitude": 125.144227
                    }
                }
            ]
        },
        "3F": {
            "Maritime Building": [
                {
                    "id": "MB3F-9",
                    "name": "BSCRIM Office",
                    "category": "Offices",
                    "floor": "3rd Floor / 3F",
                    "building": "Maritime Building",
                    "imageFileName": "bscrim-dept-office",
                    "coordinates": {
                        "latitude": 6.117082,
                        "longitude": 125.144670
                    }
                }
            ]
        },
        "4F": {
            "Susana Building": [
                {
                    "id": "SB4F-2",
                    "name": "Multimedia Center Office",
                    "category": "Offices",
                    "floor": "4th Floor / 4F",
                    "building": "Susana Building",
                    "imageFileName": "",
                    "coordinates": {
                        "latitude": 6.117367,
                        "longitude": 125.144416
                    }
                }
            ]
        }
    },
    "Rooms": {
        "1F": {
            "Old Building": [
                {
                    "id": "OB10",
                    "name": "Room 102",
                    "category": "Rooms",
                    "floor": "1st Floor / 1F / Ground",
                    "building": "Old Building",
                    "imageFileName": "bsname-dept-rm-102",
                    "coordinates": {
                        "latitude": 6.117664,
                        "longitude": 125.144416
                    }
                }
            ],
            "Maritime Building": [
                {
                    "id": "MB1F-1",
                    "name": "Engine Simulator Room",
                    "category": "Rooms",
                    "floor": "1st Floor / 1F / Ground",
                    "building": "Maritime Building",
                    "imageFileName": "engine-sim",
                    "coordinates": {
                        "latitude": 6.117348,
                        "longitude": 125.145394
                    }
                },
                {
                    "id": "MB1F-2",
                    "name": "Room 117",
                    "category": "Rooms",
                    "floor": "1st Floor / 1F / Ground",
                    "building": "Maritime Building",
                    "imageFileName": "rm117",
                    "coordinates": {
                        "latitude": 6.117325,
                        "longitude": 125.145294
                    }
                },
                {
                    "id": "MB1F-3",
                    "name": "Room 118",
                    "category": "Rooms",
                    "floor": "1st Floor / 1F / Ground",
                    "building": "Maritime Building",
                    "imageFileName": "rm118",
                    "coordinates": {
                        "latitude": 6.117305,
                        "longitude": 125.145253
                    }
                },
                {
                    "id": "MB1F-4",
                    "name": "Room 119",
                    "category": "Rooms",
                    "floor": "1st Floor / 1F / Ground",
                    "building": "Maritime Building",
                    "imageFileName": "rm119",
                    "coordinates": {
                        "latitude": 6.117285,
                        "longitude": 125.145192
                    }
                },
                {
                    "id": "MB1F-5",
                    "name": "Room 120",
                    "category": "Rooms",
                    "floor": "1st Floor / 1F / Ground",
                    "building": "Maritime Building",
                    "imageFileName": "rm120",
                    "coordinates": {
                        "latitude": 6.117260,
                        "longitude": 125.145130
                    }
                },
                {
                    "id": "MB1F-6",
                    "name": "Room 121",
                    "category": "Rooms",
                    "floor": "1st Floor / 1F / Ground",
                    "building": "Maritime Building",
                    "imageFileName": "rm121",
                    "coordinates": {
                        "latitude": 6.117227,
                        "longitude": 125.145045
                    }
                },
                {
                    "id": "MB1F-7",
                    "name": "Room 122",
                    "category": "Rooms",
                    "floor": "1st Floor / 1F / Ground",
                    "building": "Maritime Building",
                    "imageFileName": "rm122",
                    "coordinates": {
                        "latitude": 6.117208,
                        "longitude": 125.144996
                    }
                },
                {
                    "id": "MB1F-8",
                    "name": "Room 123",
                    "category": "Rooms",
                    "floor": "1st Floor / 1F / Ground",
                    "building": "Maritime Building",
                    "imageFileName": "rm123",
                    "coordinates": {
                        "latitude": 6.117181,
                        "longitude": 125.144938
                    }
                },
                {
                    "id": "MB1F-10",
                    "name": "Faculty Room",
                    "category": "Rooms",
                    "floor": "1st Floor / 1F / Ground",
                    "building": "Maritime Building",
                    "imageFileName": "faculty",
                    "coordinates": {
                        "latitude": 6.117128,
                        "longitude": 125.144800
                    }
                },
                {
                    "id": "MB1F-11",
                    "name": "Pastry Lab",
                    "category": "Rooms",
                    "floor": "1st Floor / 1F / Ground",
                    "building": "Maritime Building",
                    "imageFileName": "pastry",
                    "coordinates": {
                        "latitude": 6.117095,
                        "longitude": 125.144689
                    }
                },
                {
                    "id": "MB1F-12",
                    "name": "Room 127",
                    "category": "Rooms",
                    "floor": "1st Floor / 1F / Ground",
                    "building": "Maritime Building",
                    "imageFileName": "rm127",
                    "coordinates": {
                        "latitude": 6.117073,
                        "longitude": 125.144643
                    }
                },
                {
                    "id": "MB1F-13",
                    "name": "BSHRM Lab",
                    "category": "Rooms",
                    "floor": "1st Floor / 1F / Ground",
                    "building": "Maritime Building",
                    "imageFileName": "",
                    "coordinates": {
                        "latitude": 6.117045,
                        "longitude": 125.144577
                    }
                },
                {
                    "id": "MB1F-14",
                    "name": "HRM Dining Lab",
                    "category": "Rooms",
                    "floor": "1st Floor / 1F / Ground",
                    "building": "Maritime Building",
                    "imageFileName": "hrm-dining",
                    "coordinates": {
                        "latitude": 6.117009,
                        "longitude": 125.144543
                    }
                }
            ],
            "Susana Building": [
                {
                    "id": "SB1F-1",
                    "name": "SHS Room 01",
                    "category": "Rooms",
                    "floor": "1st Floor / 1F / Ground",
                    "building": "Susana Building",
                    "imageFileName": "rm1",
                    "coordinates": {
                        "latitude": 6.117274,
                        "longitude": 125.144459
                    }
                },
                {
                    "id": "SB1F-2",
                    "name": "SHS Room 02",
                    "category": "Rooms",
                    "floor": "1st Floor / 1F / Ground",
                    "building": "Susana Building",
                    "imageFileName": "rm2",
                    "coordinates": {
                        "latitude": 6.117351,
                        "longitude": 125.144428
                    }
                },
                {
                    "id": "SB1F-3",
                    "name": "SHS Room 03",
                    "category": "Rooms",
                    "floor": "1st Floor / 1F / Ground",
                    "building": "Susana Building",
                    "imageFileName": "rm3",
                    "coordinates": {
                        "latitude": 6.117440,
                        "longitude": 125.144396
                    }
                },
                {
                    "id": "SB1F-4",
                    "name": "SHS Room 04",
                    "category": "Rooms",
                    "floor": "1st Floor / 1F / Ground",
                    "building": "Susana Building",
                    "imageFileName": "rm4",
                    "coordinates": {
                        "latitude": 6.117514,
                        "longitude": 125.144370
                    }
                },
                {
                    "id": "SB1F-5",
                    "name": "Conference Room",
                    "category": "Rooms",
                    "floor": "1st Floor / 1F / Ground",
                    "building": "Susana Building",
                    "imageFileName": "conference",
                    "coordinates": {
                        "latitude": 6.117594,
                        "longitude": 125.144337
                    }
                }
            ],
            "Mar-E": [
                {
                    "id": "MAR1F-2",
                    "name": "Engineering Lab",
                    "category": "Rooms",
                    "floor": "1st Floor / 1F / Ground",
                    "building": "Mar-E",
                    "imageFileName": "tec-voc",
                    "coordinates": {
                        "latitude": 6.117186,
                        "longitude": 125.143981
                    }
                }
            ]
        },
        "2F": {
            "Maritime Building": [
                {
                    "id": "MB2F-1",
                    "name": "Full Mission Bridge Simulation Room",
                    "category": "Rooms",
                    "floor": "2nd Floor / 2F",
                    "building": "Maritime Building",
                    "imageFileName": "full-bridge",
                    "coordinates": {
                        "latitude": 6.117352,
                        "longitude": 125.145401
                    }
                },
                {
                    "id": "MB2F-2",
                    "name": "Briefing / Debriefing Room (F2)",
                    "category": "Rooms",
                    "floor": "2nd Floor / 2F",
                    "building": "Maritime Building",
                    "imageFileName": "brief-2f",
                    "coordinates": {
                        "latitude": 6.117330,
                        "longitude": 125.145332
                    }
                },
                {
                    "id": "MB2F-3",
                    "name": "Room 203",
                    "category": "Rooms",
                    "floor": "2nd Floor / 2F",
                    "building": "Maritime Building",
                    "imageFileName": "rm203",
                    "coordinates": {
                        "latitude": 6.117307,
                        "longitude": 125.145255
                    }
                },
                {
                    "id": "MB2F-4",
                    "name": "Room 204",
                    "category": "Rooms",
                    "floor": "2nd Floor / 2F",
                    "building": "Maritime Building",
                    "imageFileName": "rm204",
                    "coordinates": {
                        "latitude": 6.117286,
                        "longitude": 125.145199
                    }
                },
                {
                    "id": "MB2F-5",
                    "name": "Room 205",
                    "category": "Rooms",
                    "floor": "2nd Floor / 2F",
                    "building": "Maritime Building",
                    "imageFileName": "rm205",
                    "coordinates": {
                        "latitude": 6.117263,
                        "longitude": 125.145132
                    }
                },
                {
                    "id": "MB2F-6",
                    "name": "Room 206",
                    "category": "Rooms",
                    "floor": "2nd Floor / 2F",
                    "building": "Maritime Building",
                    "imageFileName": "rm206",
                    "coordinates": {
                        "latitude": 6.117226,
                        "longitude": 125.145041
                    }
                },
                {
                    "id": "MB2F-7",
                    "name": "Room 207",
                    "category": "Rooms",
                    "floor": "2nd Floor / 2F",
                    "building": "Maritime Building",
                    "imageFileName": "rm207",
                    "coordinates": {
                        "latitude": 6.117204,
                        "longitude": 125.144987
                    }
                },
                {
                    "id": "MB2F-8",
                    "name": "Room 208",
                    "category": "Rooms",
                    "floor": "2nd Floor / 2F",
                    "building": "Maritime Building",
                    "imageFileName": "rm208",
                    "coordinates": {
                        "latitude": 6.117185,
                        "longitude": 125.144934
                    }
                },
                {
                    "id": "MB2F-9",
                    "name": "Simulation Room",
                    "category": "Rooms",
                    "floor": "2nd Floor / 2F",
                    "building": "Maritime Building",
                    "imageFileName": "simul-maritime",
                    "coordinates": {
                        "latitude": 6.117161,
                        "longitude": 125.144875
                    }
                },
                {
                    "id": "MB2F-13",
                    "name": "IT Room/Storage",
                    "category": "Rooms",
                    "floor": "2nd Floor / 2F",
                    "building": "Maritime Building",
                    "imageFileName": "it-storage",
                    "coordinates": {
                        "latitude": 6.117135,
                        "longitude": 125.144811
                    }
                },
                {
                    "id": "MB2F-10",
                    "name": "Computer Lab",
                    "category": "Rooms",
                    "floor": "2nd Floor / 2F",
                    "building": "Maritime Building",
                    "imageFileName": "comlab",
                    "coordinates": {
                        "latitude": 6.117085,
                        "longitude": 125.144689
                    }
                },
                {
                    "id": "MB2F-11",
                    "name": "Housekeeping Lab",
                    "category": "Rooms",
                    "floor": "2nd Floor / 2F",
                    "building": "Maritime Building",
                    "imageFileName": "housekeeping",
                    "coordinates": {
                        "latitude": 6.117096,
                        "longitude": 125.144526
                    }
                },
                {
                    "id": "MB2F-12",
                    "name": "Bar",
                    "category": "Rooms",
                    "floor": "2nd Floor / 2F",
                    "building": "Maritime Building",
                    "imageFileName": "bar",
                    "coordinates": {
                        "latitude": 6.117006,
                        "longitude": 125.144557
                    }
                }
            ],
            "Susana Building": [
                {
                    "id": "SB2F-1",
                    "name": "Mar Computer Lab",
                    "category": "Rooms",
                    "floor": "2nd Floor / 2F",
                    "building": "Susana Building",
                    "imageFileName": "",
                    "coordinates": {
                        "latitude": 6.117285,
                        "longitude": 125.144456
                    }
                },
                {
                    "id": "SB2F-2",
                    "name": "Room 07",
                    "category": "Rooms",
                    "floor": "2nd Floor / 2F",
                    "building": "Susana Building",
                    "imageFileName": "",
                    "coordinates": {
                        "latitude": 6.117342,
                        "longitude": 125.144423
                    }
                },
                {
                    "id": "SB2F-3",
                    "name": "Room 08",
                    "category": "Rooms",
                    "floor": "2nd Floor / 2F",
                    "building": "Susana Building",
                    "imageFileName": "",
                    "coordinates": {
                        "latitude": 6.117434,
                        "longitude": 125.144394
                    }
                },
                {
                    "id": "SB2F-4",
                    "name": "Room 09",
                    "category": "Rooms",
                    "floor": "2nd Floor / 2F",
                    "building": "Susana Building",
                    "imageFileName": "",
                    "coordinates": {
                        "latitude": 6.117517,
                        "longitude": 125.144360
                    }
                },
                {
                    "id": "SB2F-5",
                    "name": "Room 10 (Susana)",
                    "category": "Rooms",
                    "floor": "2nd Floor / 2F",
                    "building": "Susana Building",
                    "imageFileName": "",
                    "coordinates": {
                        "latitude": 6.117575,
                        "longitude": 125.144341
                    }
                }
            ],
            "Mar-E": [
                {
                    "id": "MAR2F-1",
                    "name": "Room 01",
                    "category": "Rooms",
                    "floor": "2nd Floor / 2F",
                    "building": "Mar-E",
                    "imageFileName": "rm1-mar",
                    "coordinates": {
                        "latitude": 6.117173,
                        "longitude": 125.143981
                    }
                },
                {
                    "id": "MAR2F-2",
                    "name": "Room 02",
                    "category": "Rooms",
                    "floor": "2nd Floor / 2F",
                    "imageFileName": "rm2-3-4",
                    "building": "Mar-E",
                    "coordinates": {
                        "latitude": 6.117200,
                        "longitude": 125.143972
                    }
                },
                {
                    "id": "MAR2F-3",
                    "name": "Room 03",
                    "category": "Rooms",
                    "floor": "2nd Floor / 2F",
                    "building": "Mar-E",
                    "imageFileName": "rm2-3-4",
                    "coordinates": {
                        "latitude": 6.117218,
                        "longitude": 125.143979
                    }
                },
                {
                    "id": "MAR2F-4",
                    "name": "Room 04",
                    "category": "Rooms",
                    "floor": "2nd Floor / 2F",
                    "building": "Mar-E",
                    "imageFileName": "rm2-3-4",
                    "coordinates": {
                        "latitude": 6.117212,
                        "longitude": 125.143964
                    }
                },
                {
                    "id": "MAR2F-5",
                    "name": "Room 05",
                    "category": "Rooms",
                    "floor": "2nd Floor / 2F",
                    "building": "Mar-E",
                    "imageFileName": "rm5-6-7-8",
                    "coordinates": {
                        "latitude": 6.117280,
                        "longitude": 125.143953
                    }
                },
                {
                    "id": "MAR2F-6",
                    "name": "Room 06",
                    "category": "Rooms",
                    "floor": "2nd Floor / 2F",
                    "building": "Mar-E",
                    "imageFileName": "rm5-6-7-8",
                    "coordinates": {
                        "latitude": 6.117273,
                        "longitude": 125.143938
                    }
                },
                {
                    "id": "MAR2F-7",
                    "name": "Room 07",
                    "category": "Rooms",
                    "floor": "2nd Floor / 2F",
                    "building": "Mar-E",
                    "imageFileName": "rm5-6-7-8",
                    "coordinates": {
                        "latitude": 6.117336,
                        "longitude": 125.143931
                    }
                },
                {
                    "id": "MAR2F-8",
                    "name": "Room 08",
                    "category": "Rooms",
                    "floor": "2nd Floor / 2F",
                    "imageFileName": "rm5-6-7-8",
                    "building": "Mar-E",
                    "coordinates": {
                        "latitude": 6.117329,
                        "longitude": 125.143915
                    }
                },
                {
                    "id": "MAR2F-9",
                    "name": "Room 10 (Mar-E)",
                    "category": "Rooms",
                    "floor": "2nd Floor / 2F",
                    "building": "Mar-E",
                    "imageFileName": "rm10-mar",
                    "coordinates": {
                        "latitude": 6.117385,
                        "longitude": 125.143906
                    }
                },
                {
                    "id": "MAR2F-10",
                    "name": "Drawing Room I",
                    "category": "Rooms",
                    "floor": "2nd Floor / 2F",
                    "building": "Mar-E",
                    "imageFileName": "draw-mold",
                    "coordinates": {
                        "latitude": 6.117434,
                        "longitude": 125.143885
                    }
                },
                {
                    "id": "MAR2F-11",
                    "name": "Mold Lofting Room",
                    "category": "Rooms",
                    "floor": "2nd Floor / 2F",
                    "building": "Mar-E",
                    "imageFileName": "draw-mold",
                    "coordinates": {
                        "latitude": 6.117459,
                        "longitude": 125.143871
                    }
                }
            ]
        },
        "3F": {
            "Maritime Building": [
                {
                    "id": "MB3F-1",
                    "name": "Meteorology / Oceanography Lab",
                    "category": "Rooms",
                    "floor": "3rd Floor / 3F",
                    "building": "Maritime Building",
                    "imageFileName": "chart-rm301-ocean-meteo",
                    "coordinates": {
                        "latitude": 6.117301,
                        "longitude": 125.145232
                    }
                },
                {
                    "id": "MB3F-2",
                    "name": "Chart Room / Room 301",
                    "category": "Rooms",
                    "floor": "3rd Floor / 3F",
                    "building": "Maritime Building",
                    "imageFileName": "chart-rm301-ocean-meteo",
                    "coordinates": {
                        "latitude": 6.117295,
                        "longitude": 125.145218
                    }
                },
                {
                    "id": "MB3F-3",
                    "name": "GMDSS Simulator Room",
                    "category": "Rooms",
                    "floor": "3rd Floor / 3F",
                    "building": "Maritime Building",
                    "imageFileName": "gmdss",
                    "coordinates": {
                        "latitude": 6.117280,
                        "longitude": 125.145183
                    }
                },
                {
                    "id": "MB3F-4",
                    "name": "Briefing / Debriefing Room (3F)",
                    "category": "Rooms",
                    "floor": "3rd Floor / 3F",
                    "building": "Maritime Building",
                    "imageFileName": "brief-3f",
                    "coordinates": {
                        "latitude": 6.117271,
                        "longitude": 125.145160
                    }
                },
                {
                    "id": "MB3F-5",
                    "name": "Speech Lab",
                    "category": "Rooms",
                    "floor": "3rd Floor / 3F",
                    "building": "Maritime Building",
                    "imageFileName": "speech",
                    "coordinates": {
                        "latitude": 6.117249,
                        "longitude": 125.145104
                    }
                },
                {
                    "id": "MB3F-6",
                    "name": "Customs Administration Lab",
                    "category": "Rooms",
                    "floor": "3rd Floor / 3F",
                    "building": "Maritime Building",
                    "imageFileName": "customs-library",
                    "coordinates": {
                        "latitude": 6.117221,
                        "longitude": 125.145046
                    }
                },
                {
                    "id": "MB3F-7",
                    "name": "Library",
                    "category": "Rooms",
                    "floor": "3rd Floor / 3F",
                    "building": "Maritime Building",
                    "imageFileName": "customs-library",
                    "coordinates": {
                        "latitude": 6.117204,
                        "longitude": 125.145002
                    }
                },
                {
                    "id": "MB3F-8",
                    "name": "Crime Lab 1",
                    "category": "Rooms",
                    "floor": "3rd Floor / 3F",
                    "building": "Maritime Building",
                    "imageFileName": "crime-1",
                    "coordinates": {
                        "latitude": 6.117093,
                        "longitude": 125.144702
                    }
                },
                {
                    "id": "MB3F-10",
                    "name": "Crime Lab 2",
                    "category": "Rooms",
                    "floor": "3rd Floor / 3F",
                    "building": "Maritime Building",
                    "imageFileName": "crime-2-3",
                    "coordinates": {
                        "latitude": 6.117078,
                        "longitude": 125.144656
                    }
                },
                {
                    "id": "MB3F-11",
                    "name": "Crime Lab 3",
                    "category": "Rooms",
                    "floor": "3rd Floor / 3F",
                    "building": "Maritime Building",
                    "imageFileName": "crime-2-3",
                    "coordinates": {
                        "latitude": 6.117068,
                        "longitude": 125.144627
                    }
                },
                {
                    "id": "MB3F-12",
                    "name": "Alpha",
                    "category": "Rooms",
                    "floor": "3rd Floor / 3F",
                    "building": "Maritime Building",
                    "imageFileName": "alpha",
                    "coordinates": {
                        "latitude": 6.117063,
                        "longitude": 125.144619
                    }
                },
                {
                    "id": "MB3F-13",
                    "name": "Crime Scene Simulation Room",
                    "category": "Rooms",
                    "floor": "3rd Floor / 3F",
                    "building": "Maritime Building",
                    "imageFileName": "",
                    "coordinates": {
                        "latitude": 6.117036,
                        "longitude": 125.144566
                    }
                },
                {
                    "id": "MB3F-14",
                    "name": "Court Room",
                    "category": "Rooms",
                    "floor": "3rd Floor / 3F",
                    "building": "Maritime Building",
                    "imageFileName": "court",
                    "coordinates": {
                        "latitude": 6.117007,
                        "longitude": 125.144544
                    }
                },
                {
                    "id": "MB3F-15",
                    "name": "Bravo",
                    "category": "Rooms",
                    "floor": "3rd Floor / 3F",
                    "building": "Maritime Building",
                    "imageFileName": "bravo",
                    "coordinates": {
                        "latitude": 6.117081,
                        "longitude": 125.144523
                    }
                },
                {
                    "id": "MB3F-16",
                    "name": "Charlie",
                    "category": "Rooms",
                    "floor": "3rd Floor / 3F",
                    "building": "Maritime Building",
                    "imageFileName": "charlie",
                    "coordinates": {
                        "latitude": 6.117128,
                        "longitude": 125.144505
                    }
                }
            ],
            "Susana Building": [
                {
                    "id": "SB3F-1",
                    "name": "PSCAS Room / Room 11",
                    "category": "Rooms",
                    "floor": "3rd Floor / 3F",
                    "building": "Susana Building",
                    "imageFileName": "",
                    "coordinates": {
                        "latitude": 6.117268,
                        "longitude": 125.144459
                    }
                },
                {
                    "id": "SB3F-2",
                    "name": "Room 12",
                    "category": "Rooms",
                    "floor": "3rd Floor / 3F",
                    "building": "Susana Building",
                    "imageFileName": "",
                    "coordinates": {
                        "latitude": 6.117339,
                        "longitude": 125.144428
                    }
                },
                {
                    "id": "SB3F-3",
                    "name": "Room 13",
                    "category": "Rooms",
                    "floor": "3rd Floor / 3F",
                    "building": "Susana Building",
                    "imageFileName": "",
                    "coordinates": {
                        "latitude": 6.117435,
                        "longitude": 125.144392
                    }
                },
                {
                    "id": "SB3F-4",
                    "name": "Room 14",
                    "category": "Rooms",
                    "floor": "3rd Floor / 3F",
                    "building": "Susana Building",
                    "imageFileName": "",
                    "coordinates": {
                        "latitude": 6.117518,
                        "longitude": 125.144363
                    }
                },
                {
                    "id": "SB3F-5",
                    "name": "Room 15",
                    "category": "Rooms",
                    "floor": "3rd Floor / 3F",
                    "building": "Susana Building",
                    "imageFileName": "",
                    "coordinates": {
                        "latitude": 6.117574,
                        "longitude": 125.144341
                    }
                }
            ]
        },
        "4F": {
            "Susana Building": [
                {
                    "id": "SB4F-1",
                    "name": "Audio Visual Room",
                    "category": "Rooms",
                    "floor": "4th Floor / 4F",
                    "building": "Susana Building",
                    "imageFileName": "",
                    "coordinates": {
                        "latitude": 6.117300,
                        "longitude": 125.144441
                    }
                },
                {
                    "id": "SB4F-3",
                    "name": "Physics Lab",
                    "category": "Rooms",
                    "floor": "4th Floor / 4F",
                    "building": "Susana Building",
                    "imageFileName": "",
                    "coordinates": {
                        "latitude": 6.117464,
                        "longitude": 125.144377
                    }
                },
                {
                    "id": "SB4F-4",
                    "name": "Nat. Science Lab",
                    "category": "Rooms",
                    "floor": "4th Floor / 4F",
                    "building": "Susana Building",
                    "imageFileName": "",
                    "coordinates": {
                        "latitude": 6.117500,
                        "longitude": 125.144367
                    }
                },
                {
                    "id": "SB4F-5",
                    "name": "Chemistry Lab",
                    "category": "Rooms",
                    "floor": "4th Floor / 4F",
                    "building": "Susana Building",
                    "imageFileName": "",
                    "coordinates": {
                        "latitude": 6.117559,
                        "longitude": 125.144344
                    }
                }
            ]
        }
    },
    "Toilets": {
        "1F": [
            {
                "id": "CR1F-1",
                "name": "Maritime CR Male (1F)",
                "category": "Toilets",
                "floor": "1st Floor / 1F / Ground",
                "imageFileName": "maritime-m-cr-1",
                "coordinates": {
                    "latitude": 6.117227,
                    "longitude": 125.145109
                }
            },
            {
                "id": "CR1F-2",
                "name": "Maritime CR Female (1F)",
                "category": "Toilets",
                "floor": "1st Floor / 1F / Ground",
                "imageFileName": "maritime-f-cr-1",
                "coordinates": {
                    "latitude": 6.117082,
                    "longitude": 125.144732
                }
            },
            {
                "id": "CR1F-3",
                "name": "Mar-E CR",
                "category": "Toilets",
                "floor": "1st Floor / 1F / Ground",
                "imageFileName": "mar-cr",
                "coordinates": {
                    "latitude": 6.117185,
                    "longitude": 125.143971
                }
            },
            {
                "id": "CR1F-4",
                "name": "Back of Canteen CR",
                "category": "Toilets",
                "floor": "1st Floor / 1F / Ground",
                "imageFileName": "canteen-cr",
                "coordinates": {
                    "latitude": 6.117612,
                    "longitude": 125.144203
                }
            }
        ],
        "2F": [
            {
                "id": "CR2F-1",
                "name": "Maritime CR (2F)",
                "category": "Toilets",
                "floor": "2nd Floor / 2F",
                "imageFileName": "maritme-cr-2",
                "coordinates": {
                    "latitude": 6.117224,
                    "longitude": 125.145117
                }
            },
            {
                "id": "CR2F-2",
                "name": "Maritime CR Female (2F)",
                "category": "Toilets",
                "floor": "2nd Floor / 2F",
                "imageFileName": "maritime-cr-f-2",
                "coordinates": {
                    "latitude": 6.117079,
                    "longitude": 125.144730
                }
            },
            {
                "id": "CR2F-3",
                "name": "Susana CR (2F)",
                "category": "Toilets",
                "floor": "2nd Floor / 2F",
                "imageFileName": "",
                "coordinates": {
                    "latitude": 6.117689,
                    "longitude": 125.144246
                }
            }
        ],
        "3F": [
            {
                "id": "CR3F-1",
                "name": "Susana CR (3F)",
                "category": "Toilets",
                "floor": "3rd Floor / 3F",
                "imageFileName": "",
                "coordinates": {
                    "latitude": 6.117687,
                    "longitude": 125.144246
                }
            }
        ],
        "4F": [
            {
                "id": "CR4F-1",
                "name": "Susana CR (4F)",
                "category": "Toilets",
                "floor": "4th Floor / 4F",
                "imageFileName": "",
                "coordinates": {
                    "latitude": 6.117690,
                    "longitude": 125.144245
                }
            }
        ]
    },
    "Outdoors": [
        {
            "id": "GB1",
            "name": "Gym",
            "category": "Outdoors",
            "floor": "1st Floor / 1F / Ground",
            "imageFileName": "gym",
            "coordinates": {
                "latitude": 6.117617,
                "longitude": 125.145000
            }
        },
        {
            "id": "O-1",
            "name": "Canteen",
            "category": "Outdoors",
            "floor": "1st Floor / 1F / Ground",
            "imageFileName": "canteen",
            "coordinates": {
                "latitude": 6.117333,
                "longitude": 125.144223
            }
        },
        {
            "id": "O-2",
            "name": "Swimming Area",
            "floor": "1st Floor / 1F / Ground",
            "category": "Outdoors",
            "imageFileName": "swim",
            "coordinates": {
                "latitude": 6.116813,
                "longitude": 125.144650
            }
        }
    ]
}